odoo/addons/document_page_access_group/README.rst
odoo/addons/document_page_access_group/__init__.py
odoo/addons/document_page_access_group/__manifest__.py
odoo/addons/document_page_access_group/i18n/ca.po
odoo/addons/document_page_access_group/i18n/document_page_access_group.pot
odoo/addons/document_page_access_group/i18n/es.po
odoo/addons/document_page_access_group/i18n/it.po
odoo/addons/document_page_access_group/i18n/pt_BR.po
odoo/addons/document_page_access_group/models/__init__.py
odoo/addons/document_page_access_group/models/document_page.py
odoo/addons/document_page_access_group/readme/CONTRIBUTORS.md
odoo/addons/document_page_access_group/readme/DESCRIPTION.md
odoo/addons/document_page_access_group/readme/USAGE.md
odoo/addons/document_page_access_group/security/security.xml
odoo/addons/document_page_access_group/static/description/icon.png
odoo/addons/document_page_access_group/static/description/index.html
odoo/addons/document_page_access_group/tests/__init__.py
odoo/addons/document_page_access_group/tests/common.py
odoo/addons/document_page_access_group/tests/test_document_page_access_group.py
odoo/addons/document_page_access_group/views/document_page.xml
odoo_addon_document_page_access_group-18.0.1.0.1.dist-info/METADATA
odoo_addon_document_page_access_group-18.0.1.0.1.dist-info/WHEEL
odoo_addon_document_page_access_group-18.0.1.0.1.dist-info/top_level.txt
odoo_addon_document_page_access_group-18.0.1.0.1.dist-info/RECORD
