Metadata-Version: 2.1
Name: odoo-addon-document_page_access_group
Version: 18.0.1.0.1
Requires-Python: >=3.10
Requires-Dist: odoo-addon-document_knowledge==18.0.*
Requires-Dist: odoo-addon-document_page==18.0.*
Requires-Dist: odoo==18.0.*
Summary: Choose groups to access document pages
Home-page: https://github.com/OCA/knowledge
License: AGPL-3
Author: Sygel, Creu Blanca, Odoo Community Association (OCA)
Author-email: support@odoo-community.org
Classifier: Programming Language :: Python
Classifier: Framework :: Odoo
Classifier: Framework :: Odoo :: 18.0
Classifier: License :: OSI Approved :: GNU Affero General Public License v3
